<?xml version="1.0" encoding="UTF-8"?> <!--NOTE: XML BLURB MUST BE FIRST THING IN DOCUMENT!!-->
<users>
    <user>
        <email>ryan@ryanheise.com</email>
        <name>Ryan Heise</name>
        <password>blahblah</password>
        <dob>12/08/1993</dob>
        <isAdmin>true</isAdmin>
    </user>
    <user>
        <email>joe@bloggs.com</email>
        <name>Joe Bloggs</name>
        <password>foobar</password>
        <dob>02/06/1990</dob>
        <isAdmin>false</isAdmin>
    </user>
</users>